{
    "justoverclock-steam-api": {
        "admin": {
            "steamApiKey": "Steam Api Key",
            "steamApiKey-help": "Get your FREE api key on https://steamcommunity.com/dev/apikey"
        },
        "forum": {
            "steamId": "Steam Profile ID",
            "steamIdSaved": "Steam id saved successfully",
            "LatestGamesPlayed": "Latest Games Played",
            "statusOffline": "Offline",
            "statusOnline": "Online",
            "statusBusy": "Busy",
            "statusAway": "Away",
            "statusSnooze": "Snooze",
            "statusTrade": "Looking To Trade",
            "statusPlay": "Looking To Play",
            "lastLogin": "Last Login: ",
            "status": "Status: ",
            "country": "Country: ",
            "gamesOwned": "Games Owned: ",
            "visitProfile": "Visit Profile",
            "realName": "Real Name: ",
            "accountCreated": "Member since: "
        }
    }
}
