{
    "nearata-embed-twitch": {
        "admin": {
            "allowfullscreen": "Allow fullscreen",
            "autoplay": "Autoplay"
        },
        "forum": {
            "modal": {
                "label": {
                    "collection": "Collection ID",
                    "channel": "Channel Name",
                    "layout": "Layout",
                    "type": "Type of content",
                    "video": "Video ID"
                },
                "save_changes": "Save Changes",
                "options": {
                    "channel": "Channel",
                    "video": "Video",
                    "collection": "Collection"
                }
            },
            "button_tooltip_title": "Embed Twitch"
        }
    }
}
