{
    "tohsakarat-tags-filter": {
        "forum": {
            "index_page": {
                "filter_tags": {
                    "accessible_label": "tags filter",
                    "all": "all",
                    "label": "{text}",
                    "search_label": "Search...",
                    "no_results": "No results",
                    "start_typing": "Start typing...",
                    "keep_typing": "Typing...",
                    "remove_filter": "stop searching;",
                    "comment_filter": "Click pinned tags to cancel~"
                }
            }
        }
    }
}
